picle/__init__.py
picle/cache.py
picle/models.py
picle/picle.py
picle/utils.py
picle-0.9.2.dist-info/LICENSE
picle-0.9.2.dist-info/METADATA
picle-0.9.2.dist-info/WHEEL
picle-0.9.2.dist-info/RECORD
