Metadata-Version: 2.3
Name: picle
Version: 0.9.2
Summary: Python Interactive Command Line Shells
License: MIT
Author: Denis Mulyalin
Author-email: d.mulyalin@gmail.com
Requires-Python: >=3.9,<4.0
Classifier: License :: OSI Approved :: MIT License
Classifier: Programming Language :: Python :: 3
Classifier: Programming Language :: Python :: 3.9
Classifier: Programming Language :: Python :: 3.10
Classifier: Programming Language :: Python :: 3.11
Classifier: Programming Language :: Python :: 3.12
Classifier: Programming Language :: Python :: 3.13
Provides-Extra: full
Requires-Dist: pydantic (>=2.0.1,<3.0.0)
Requires-Dist: pyreadline3 (==3.4.1) ; sys_platform == "win32"
Requires-Dist: pyyaml (==6.0.2) ; extra == "full"
Requires-Dist: rich (>=13.0.0,<15.0.0) ; extra == "full"
Requires-Dist: tabulate (==0.9.0) ; extra == "full"
Project-URL: Documentation, https://dmulyalin.github.io/picle/
Project-URL: Homepage, https://github.com/dmulyalin/picle
Project-URL: Repository, https://github.com/dmulyalin/picle
